athenapp/__init__.py
athenapp/pyathena/__init__.py
athenapp/pydrum/__init__.py
athenapp/pydrum/diagnostics.py
athenapp/pydrum/plots1d.py
athenapp/pydrum/plots2d.py
athenapp/pyharp/__init__.py
athenapp-0.0.4.dist-info/LICENCE
athenapp-0.0.4.dist-info/METADATA
athenapp-0.0.4.dist-info/WHEEL
athenapp-0.0.4.dist-info/top_level.txt
athenapp-0.0.4.dist-info/RECORD
