Metadata-Version: 2.1
Name: athenapp
Version: 0.0.4
Summary: python extension for Athena/HARP
Home-page: https://github.com/luminoctum/athena-harp
Author: Cheng Li
Author-email: cli@gps.caltech.edu
License: UNKNOWN
Platform: UNKNOWN
Classifier: Programming Language :: Python :: 3
Classifier: License :: OSI Approved :: MIT License
Classifier: Operating System :: OS Independent
Requires-Python: >=2.7
Requires-Dist: numpy (>=1.13)
Provides-Extra: dev
Provides-Extra: docs
Requires-Dist: sphinx ; extra == 'docs'
Requires-Dist: sphinx-rtd-theme ; extra == 'docs'
